{
  "targetAttributes": [
    "type",
    "cssclass"
  ],
  "targetTags": true,
  "getFromInlineField": true,
  "enableTabHeader": true,
  "activateSnippet": true,
  "enableEditor": true,
  "enableFileList": true,
  "enableBacklinks": true,
  "enableQuickSwitcher": true,
  "enableSuggestor": true,
  "selectors": [
    {
      "type": "attribute",
      "name": "type",
      "value": "book",
      "matchCaseSensitive": false,
      "match": "exact",
      "uid": "70c8-2a42",
      "selectText": true,
      "selectAppend": false,
      "selectPrepend": true,
      "selectBackground": false
    }
  ]
}